django_crypto_extensions/__init__.py
django_crypto_extensions/django_fields.py
django_crypto_extensions/drf_fields.py
django_crypto_extensions/tests/__init__.py
django_crypto_extensions/tests/apps.py
django_crypto_extensions/tests/models.py
django_crypto_extensions/tests/settings.py
django_crypto_extensions-1.0.2.dist-info/LICENSE
django_crypto_extensions-1.0.2.dist-info/METADATA
django_crypto_extensions-1.0.2.dist-info/WHEEL
django_crypto_extensions-1.0.2.dist-info/top_level.txt
django_crypto_extensions-1.0.2.dist-info/RECORD
