Metadata-Version: 2.1
Name: django-crypto-extensions
Version: 1.0.2
Summary: Extensions for Django in terms of Cryptography.
Home-page: https://github.com/DjangoCrypto/django-crypto-extensions
Author: DjangoCrypto
Author-email: kamil1marczak@gmail.com
License: MIT
Platform: UNKNOWN
Classifier: Environment :: Web Environment
Classifier: Framework :: Django
Classifier: Intended Audience :: Developers
Classifier: Operating System :: OS Independent
Classifier: License :: OSI Approved :: BSD License
Classifier: Programming Language :: Python
Classifier: Programming Language :: Python :: 3
Classifier: Programming Language :: Python :: 3.6
Classifier: Programming Language :: Python :: 3.7
Classifier: Programming Language :: Python :: 3.8
Classifier: Programming Language :: Python :: 3.9
Classifier: Topic :: Internet :: WWW/HTTP
Classifier: Topic :: Internet :: WWW/HTTP :: Dynamic Content
Requires-Python: >=3.6
License-File: LICENSE
Requires-Dist: Django (>=2.2)
Requires-Dist: djangorestframework (>=3.9.2)
Requires-Dist: cryptography (==3.4.7)
Requires-Dist: setuptools (==57.0.0)
